matrix/__init__.py
matrix/cholesky_decomposition.py
matrix/eigenvalue_decomposition.py
matrix/lu_decomposition.py
matrix/maths.py
matrix/matrix.py
matrix/qr_decomposition.py
matrix/singular_value_decomposition.py
impact_matrix-0.0.1.dist-info/METADATA
impact_matrix-0.0.1.dist-info/WHEEL
impact_matrix-0.0.1.dist-info/top_level.txt
impact_matrix-0.0.1.dist-info/RECORD
