Metadata-Version: 2.4
Name: impact-matrix
Version: 0.0.1
Summary: This is a Python reimplementation of the Java Jama package utilized in the original Imapct Java application - https://sourceforge.net/projects/impact/  The original Java code was implemented by The MathWorks, Inc. and the National Institute of Standards and Technology.  This code implents version 5 from August 1998
Author-email: Peter Harding <plh@performiq.com>
Project-URL: Homepage, https://gitlab.com/impact-analysis/impact-matrix
Project-URL: Repository, https://gitlab.com/impact-analysis/impact-matrix
Classifier: Programming Language :: Python :: 3
Classifier: Programming Language :: Python :: 3 :: Only
Classifier: License :: OSI Approved :: GNU General Public License v2 (GPLv2)
Classifier: Operating System :: OS Independent
Requires-Python: >=3.10
Provides-Extra: test
Requires-Dist: pytest>=8; extra == "test"
